webctl/__init__.py
webctl/__main__.py
webctl/config.py
webctl/exceptions.py
webctl/cli/__init__.py
webctl/cli/app.py
webctl/cli/output.py
webctl/cli/commands/__init__.py
webctl/daemon/__init__.py
webctl/daemon/event_emitter.py
webctl/daemon/server.py
webctl/daemon/session_manager.py
webctl/daemon/detectors/__init__.py
webctl/daemon/detectors/action.py
webctl/daemon/detectors/auth.py
webctl/daemon/detectors/cookie_banner.py
webctl/daemon/detectors/view_change.py
webctl/daemon/handlers/__init__.py
webctl/daemon/handlers/console.py
webctl/daemon/handlers/error_screenshot.py
webctl/daemon/handlers/hitl.py
webctl/daemon/handlers/interact.py
webctl/daemon/handlers/navigation.py
webctl/daemon/handlers/observe.py
webctl/daemon/handlers/registry.py
webctl/daemon/handlers/session.py
webctl/daemon/handlers/wait.py
webctl/protocol/__init__.py
webctl/protocol/client.py
webctl/protocol/credentials.py
webctl/protocol/messages.py
webctl/protocol/transport.py
webctl/query/__init__.py
webctl/query/ast.py
webctl/query/grammar.py
webctl/query/parser.py
webctl/query/resolver.py
webctl/security/__init__.py
webctl/security/domain_policy.py
webctl/views/__init__.py
webctl/views/a11y.py
webctl/views/dom_lite.py
webctl/views/filters.py
webctl/views/markdown.py
webctl/views/redaction.py
webctl-0.3.1.dist-info/METADATA
webctl-0.3.1.dist-info/WHEEL
webctl-0.3.1.dist-info/entry_points.txt
webctl-0.3.1.dist-info/RECORD
