Metadata-Version: 2.4
Name: webctl
Version: 0.3.1
Summary: Browser automation via CLI — for humans and agents
Project-URL: Homepage, https://github.com/cosinusalpha/webctl
Project-URL: Repository, https://github.com/cosinusalpha/webctl
Project-URL: Issues, https://github.com/cosinusalpha/webctl/issues
Author-email: cosinusalpha <42695699+cosinusalpha@users.noreply.github.com>
License: MIT
Keywords: agent,automation,browser,cli,web
Classifier: Development Status :: 3 - Alpha
Classifier: Environment :: Console
Classifier: Intended Audience :: Developers
Classifier: License :: OSI Approved :: MIT License
Classifier: Operating System :: OS Independent
Classifier: Programming Language :: Python :: 3.11
Classifier: Programming Language :: Python :: 3.12
Classifier: Topic :: Internet :: WWW/HTTP :: Browsers
Classifier: Topic :: Software Development :: Testing
Requires-Python: >=3.11
Requires-Dist: aiofiles>=24.0.0
Requires-Dist: lark>=1.1.0
Requires-Dist: markdownify>=0.13.0
Requires-Dist: playwright>=1.40.0
Requires-Dist: pydantic>=2.0.0
Requires-Dist: rich>=13.0.0
Requires-Dist: typer>=0.12.0
Provides-Extra: dev
Requires-Dist: mypy>=1.10.0; extra == 'dev'
Requires-Dist: pytest-asyncio>=0.23.0; extra == 'dev'
Requires-Dist: pytest-playwright>=0.5.0; extra == 'dev'
Requires-Dist: pytest>=8.0.0; extra == 'dev'
Requires-Dist: ruff>=0.4.0; extra == 'dev'
Requires-Dist: types-aiofiles>=24.0.0; extra == 'dev'
